fn_api_wrapper/__init__.py
fn_api_wrapper-3.0.3.dist-info/LICENSE
fn_api_wrapper-3.0.3.dist-info/METADATA
fn_api_wrapper-3.0.3.dist-info/WHEEL
fn_api_wrapper-3.0.3.dist-info/top_level.txt
fn_api_wrapper-3.0.3.dist-info/RECORD
