Metadata-Version: 2.1
Name: fn-api-wrapper
Version: 3.0.3
Summary: API wrapper for https://fortnite-api.com
Home-page: https://github.com/LupusLeaks/fortnite-api-wrapper
Author: LupusLeaks
Author-email: LupusLeaks@gmail.com
License: UNKNOWN
Platform: UNKNOWN
Classifier: Programming Language :: Python :: 3
Classifier: License :: OSI Approved :: MIT License
Classifier: Operating System :: OS Independent
Requires-Python: >=3.6
Requires-Dist: requests
